symantic/DimensionalFeatureSpaceConstruction.py
symantic/DimensionalRegressor.py
symantic/FeatureSpaceConstruction.py
symantic/Regressor.py
symantic/__init__.py
symantic/model.py
symantic/pareto_new.py
symantic-1.1.0.6.dist-info/METADATA
symantic-1.1.0.6.dist-info/WHEEL
symantic-1.1.0.6.dist-info/top_level.txt
symantic-1.1.0.6.dist-info/RECORD
