Metadata-Version: 2.1
Name: symantic
Version: 1.1.0.6
Summary: UNKNOWN
Home-page: UNKNOWN
Author: Madhav Muthyala
Author-email: madhavreddymuthyala@gmail.com
License: UNKNOWN
Platform: UNKNOWN
Classifier: Programming Language :: Python :: 3
Classifier: License :: OSI Approved :: MIT License
Classifier: Operating System :: OS Independent
Requires-Python: >=3.6
Requires-Dist: torch
Requires-Dist: pandas (==2.0.0)
Requires-Dist: numpy (==1.23.5)
Requires-Dist: scipy (==1.10.1)
Requires-Dist: scikit-learn (==1.2.2)
